solmate_sdk/__init__.py
solmate_sdk/apiclient.py
solmate_sdk/connection.py
solmate_sdk/tests.py
solmate_sdk/utils.py
solmate_sdk-0.1.11.dist-info/LICENSE.md
solmate_sdk-0.1.11.dist-info/METADATA
solmate_sdk-0.1.11.dist-info/WHEEL
solmate_sdk-0.1.11.dist-info/RECORD
