Metadata-Version: 2.1
Name: solmate-sdk
Version: 0.1.11
Summary: Software Development Kit for the EET SolMate
Home-page: https://github.com/eet-energy/solmate-sdk
License: MIT
Author: EET
Requires-Python: >=3.8,<4.0
Classifier: License :: OSI Approved :: MIT License
Classifier: Programming Language :: Python :: 3
Classifier: Programming Language :: Python :: 3.8
Classifier: Programming Language :: Python :: 3.9
Classifier: Programming Language :: Python :: 3.10
Classifier: Programming Language :: Python :: 3.11
Classifier: Programming Language :: Python :: 3.12
Requires-Dist: websockets (==11.0.3)
Project-URL: Documentation, https://solmate-sdk.readthedocs.io/en/latest/
Project-URL: Repository, https://github.com/eet-energy/solmate-sdk
